jsonengine/__init__.py
jsonengine-1.0.5.dist-info/LICENSE
jsonengine-1.0.5.dist-info/METADATA
jsonengine-1.0.5.dist-info/WHEEL
jsonengine-1.0.5.dist-info/top_level.txt
jsonengine-1.0.5.dist-info/RECORD
